pkg_info.py
pkg_info-0.1.2.dist-info/DESCRIPTION.rst
pkg_info-0.1.2.dist-info/METADATA
pkg_info-0.1.2.dist-info/RECORD
pkg_info-0.1.2.dist-info/WHEEL
pkg_info-0.1.2.dist-info/metadata.json
pkg_info-0.1.2.dist-info/top_level.txt
