Metadata-Version: 2.0
Name: pkg-info
Version: 0.1.2
Summary: Tiny library to fetch package info from PyPI.
Home-page: https://github.com/acifani/pkg-info
Author: Alessandro Cifani
Author-email: alessandro.cifani@gmail.com
License: BSD
Platform: UNKNOWN
Classifier: Development Status :: 3 - Alpha
Classifier: Intended Audience :: Developers
Classifier: License :: OSI Approved :: BSD License
Classifier: Operating System :: OS Independent
Classifier: Topic :: Software Development :: Libraries :: Python Modules
Classifier: Programming Language :: Python
Requires-Dist: requests
